execution-asserts/__init__.py
execution_asserts/__init__.py
execution_assets/__init__.py
execution_asserts-0.0.3.dist-info/LICENSE
execution_asserts-0.0.3.dist-info/METADATA
execution_asserts-0.0.3.dist-info/WHEEL
execution_asserts-0.0.3.dist-info/top_level.txt
execution_asserts-0.0.3.dist-info/RECORD
